main.py
xulantest-0.1.7.dist-info/licenses/LICENSE
xulantest-0.1.7.dist-info/METADATA
xulantest-0.1.7.dist-info/WHEEL
xulantest-0.1.7.dist-info/top_level.txt
xulantest-0.1.7.dist-info/RECORD
