Metadata-Version: 2.4
Name: xulantest
Version: 0.1.7
Summary: XuLan test
License: MIT
Keywords: test
Classifier: Development Status :: 1 - Planning
Classifier: Intended Audience :: Developers
Classifier: License :: OSI Approved :: MIT License
Classifier: Programming Language :: Python :: 3
Requires-Python: >=3.9
License-File: LICENSE
Dynamic: license-file
